shakespeare_translate.py
shakespeare_translate-0.0.0.dist-info/LICENSE
shakespeare_translate-0.0.0.dist-info/METADATA
shakespeare_translate-0.0.0.dist-info/WHEEL
shakespeare_translate-0.0.0.dist-info/top_level.txt
shakespeare_translate-0.0.0.dist-info/RECORD
